myfy/__init__.py
myfy/version.py
myfy-0.1.2.dist-info/METADATA
myfy-0.1.2.dist-info/WHEEL
myfy-0.1.2.dist-info/RECORD
