Metadata-Version: 2.4
Name: myfy
Version: 0.1.2
Summary: Opinionated Python framework with modularity, ergonomics, and power
Requires-Python: >=3.12
Requires-Dist: myfy-cli~=0.1.2
Requires-Dist: myfy-core~=0.1.2
Provides-Extra: all
Requires-Dist: myfy-frontend~=0.1.0; extra == 'all'
Requires-Dist: myfy-web~=0.1.2; extra == 'all'
Provides-Extra: frontend
Requires-Dist: myfy-frontend~=0.1.0; extra == 'frontend'
Provides-Extra: web
Requires-Dist: myfy-web~=0.1.2; extra == 'web'
